{
    "Version": "2012-10-17",
    "Statement": [
        {
            "Sid": "LambdaFunctionAccess",
            "Effect": "Allow",
            "Action": [
                "lambda:UpdateFunctionCode",
                "lambda:UpdateFunctionConfiguration",
                "lambda:GetFunction",
                "lambda:CreateFunction",
                "lambda:TagResource",
                "lambda:UntagResource",
                "lambda:ListTags",
                "lambda:PublishVersion",
                "lambda:GetFunctionConfiguration"
            ],
            "Resource": "arn:aws:lambda:*:*:function:*"
        },
        {
            "Sid": "IAMRoleAccess",
            "Effect": "Allow",
            "Action": [
                "iam:PassRole"
            ],
            "Resource": "arn:aws:iam::*:role/lambda-execution-role*"
        },
        {
            "Sid": "S3Access",
            "Effect": "Allow",
            "Action": [
                "s3:GetObject",
                "s3:PutObject"
            ],
            "Resource": [
                "*"
            ]
        },
        {
            "Sid": "LogsAccess",
            "Effect": "Allow",
            "Action": [
                "logs:CreateLogGroup",
                "logs:CreateLogStream",
                "logs:PutLogEvents",
                "logs:DescribeLogGroups",
                "logs:DescribeLogStreams"
            ],
            "Resource": "arn:aws:logs:*:*:*"
        }
    ]
}